libia_test/__init__.py
libia_test/profile.py
libia_test/version.py
libia_test/wafl.py
libia_test-0.0.8.dist-info/LICENSE
libia_test-0.0.8.dist-info/METADATA
libia_test-0.0.8.dist-info/WHEEL
libia_test-0.0.8.dist-info/top_level.txt
libia_test-0.0.8.dist-info/RECORD
