Metadata-Version: 2.1
Name: libia-test
Version: 0.0.8
Summary: IA Unit Testing Utils
License-File: LICENSE
Requires-Dist: python-afl
Requires-Dist: line-profiler
Provides-Extra: rel
Requires-Dist: twine ; extra == 'rel'
Provides-Extra: test
Requires-Dist: coverage ; extra == 'test'
Requires-Dist: line-profiler ; extra == 'test'
Requires-Dist: mypy ; extra == 'test'
Requires-Dist: pylint ; extra == 'test'
Requires-Dist: pytest ; extra == 'test'
Requires-Dist: pytest-line-profiler ; extra == 'test'
Requires-Dist: pytest-mypy ; extra == 'test'
Requires-Dist: pytest-pylint ; extra == 'test'
